Metadata-Version: 2.1
Name: clonosGP
Version: 1.0
Summary: Clonal deconvolution in cancer using longitudinal NGS data
Home-page: http://github.com/dvav/clonosGP
Author: Dimitrios V. Vavoulis
Author-email: dimitris.vavoulis@gmail.com
License: MIT
Platform: UNKNOWN
Classifier: Programming Language :: Python :: 3
Classifier: License :: OSI Approved :: MIT License
Classifier: Operating System :: OS Independent
Classifier: Intended Audience :: Science/Research
Classifier: Topic :: Scientific/Engineering :: Bio-Informatics
Requires-Python: >=3.7
